intranetflow/__init__.py
intranetflow/netcore.py
rwoka-0.1.3.dist-info/LICENSE
rwoka-0.1.3.dist-info/METADATA
rwoka-0.1.3.dist-info/WHEEL
rwoka-0.1.3.dist-info/entry_points.txt
rwoka-0.1.3.dist-info/top_level.txt
rwoka-0.1.3.dist-info/RECORD
