Metadata-Version: 2.1
Name: rwoka
Version: 0.1.3
Summary: Simplified HTTP requests and GitHub package installer.
Home-page: https://github.com/marryqueen2024/intranetflow
Author: marry queen
Author-email: marryqueen2024@hotmail.com
License: MIT
Keywords: intranetflow https
Classifier: Programming Language :: Python :: 3.12
Classifier: Programming Language :: Python :: 3.11
Classifier: Programming Language :: Python :: 3.13
Classifier: License :: OSI Approved :: MIT License
Classifier: Operating System :: OS Independent
Requires-Python: >=3.9
License-File: LICENSE
Requires-Dist: requests
